{
  "left": {
    "roundOf32": [
      {
        "id": "L_roundOf32_0",
        "team1": {
          "name": "Germany (0.0%)",
          "code": "GER",
          "score": "L",
          "winner": false
        },
        "team2": {
          "name": "Paraguay (100.0%)",
          "code": "PAR",
          "score": "W",
          "winner": true
        }
      },
      {
        "id": "L_roundOf32_1",
        "team1": {
          "name": "France (100.0%)",
          "code": "FRA",
          "score": "W",
          "winner": true
        },
        "team2": {
          "name": "Sweden (0.0%)",
          "code": "SWE",
          "score": "L",
          "winner": false
        }
      },
      {
        "id": "L_roundOf32_2",
        "team1": {
          "name": "Canada (100.0%)",
          "code": "CAN",
          "score": "W",
          "winner": true
        },
        "team2": {
          "name": "South Africa (0.0%)",
          "code": "RSA",
          "score": "L",
          "winner": false
        }
      },
      {
        "id": "L_roundOf32_3",
        "team1": {
          "name": "Morocco (100.0%)",
          "code": "MAR",
          "score": "W",
          "winner": true
        },
        "team2": {
          "name": "Netherlands (0.0%)",
          "code": "NED",
          "score": "L",
          "winner": false
        }
      },
      {
        "id": "L_roundOf32_4",
        "team1": {
          "name": "Brazil (100.0%)",
          "code": "BRA",
          "score": "W",
          "winner": true
        },
        "team2": {
          "name": "Japan (0.0%)",
          "code": "JPN",
          "score": "L",
          "winner": false
        }
      },
      {
        "id": "L_roundOf32_5",
        "team1": {
          "name": "Ivory Coast (0.0%)",
          "code": "CIV",
          "score": "L",
          "winner": false
        },
        "team2": {
          "name": "Norway (100.0%)",
          "code": "NOR",
          "score": "W",
          "winner": true
        }
      },
      {
        "id": "L_roundOf32_6",
        "team1": {
          "name": "Ecuador (0.0%)",
          "code": "ECU",
          "score": "L",
          "winner": false
        },
        "team2": {
          "name": "Mexico (100.0%)",
          "code": "MEX",
          "score": "W",
          "winner": true
        }
      },
      {
        "id": "L_roundOf32_7",
        "team1": {
          "name": "DR Congo (0.0%)",
          "code": "DRC",
          "score": "L",
          "winner": false
        },
        "team2": {
          "name": "England (100.0%)",
          "code": "ENG",
          "score": "W",
          "winner": true
        }
      }
    ],
    "roundOf16": [
      {
        "id": "L_roundOf16_0",
        "team1": {
          "name": "Paraguay (25.9%)",
          "code": "PAR",
          "score": "L",
          "winner": false
        },
        "team2": {
          "name": "France (74.1%)",
          "code": "FRA",
          "score": "W",
          "winner": true
        }
      },
      {
        "id": "L_roundOf16_1",
        "team1": {
          "name": "Canada (48.0%)",
          "code": "CAN",
          "score": "L",
          "winner": false
        },
        "team2": {
          "name": "Morocco (52.0%)",
          "code": "MAR",
          "score": "W",
          "winner": true
        }
      },
      {
        "id": "L_roundOf16_2",
        "team1": {
          "name": "Brazil (58.1%)",
          "code": "BRA",
          "score": "W",
          "winner": true
        },
        "team2": {
          "name": "Norway (41.9%)",
          "code": "NOR",
          "score": "L",
          "winner": false
        }
      },
      {
        "id": "L_roundOf16_3",
        "team1": {
          "name": "Mexico (49.7%)",
          "code": "MEX",
          "score": "L",
          "winner": false
        },
        "team2": {
          "name": "England (50.3%)",
          "code": "ENG",
          "score": "W",
          "winner": true
        }
      }
    ],
    "quarterFinals": [
      {
        "id": "L_quarterFinals_0",
        "team1": {
          "name": "France (69.6%)",
          "code": "FRA",
          "score": "W",
          "winner": true
        },
        "team2": {
          "name": "Morocco (30.4%)",
          "code": "MAR",
          "score": "L",
          "winner": false
        }
      },
      {
        "id": "L_quarterFinals_1",
        "team1": {
          "name": "Brazil (48.7%)",
          "code": "BRA",
          "score": "L",
          "winner": false
        },
        "team2": {
          "name": "England (51.3%)",
          "code": "ENG",
          "score": "W",
          "winner": true
        }
      }
    ],
    "semiFinals": [
      {
        "id": "L_semiFinals_0",
        "team1": {
          "name": "France (57.4%)",
          "code": "FRA",
          "score": "W",
          "winner": true
        },
        "team2": {
          "name": "England (42.6%)",
          "code": "ENG",
          "score": "L",
          "winner": false
        }
      }
    ]
  },
  "right": {
    "roundOf32": [
      {
        "id": "R_roundOf32_0",
        "team1": {
          "name": "Colombia (81.4%)",
          "code": "COL",
          "score": "W",
          "winner": true
        },
        "team2": {
          "name": "Ghana (18.6%)",
          "code": "GHA",
          "score": "L",
          "winner": false
        }
      },
      {
        "id": "R_roundOf32_1",
        "team1": {
          "name": "Austria (26.0%)",
          "code": "AUT",
          "score": "L",
          "winner": false
        },
        "team2": {
          "name": "Spain (74.0%)",
          "code": "ESP",
          "score": "W",
          "winner": true
        }
      },
      {
        "id": "R_roundOf32_2",
        "team1": {
          "name": "Bosnia and Herzegovina (29.3%)",
          "code": "BIH",
          "score": "L",
          "winner": false
        },
        "team2": {
          "name": "United States (70.7%)",
          "code": "USA",
          "score": "W",
          "winner": true
        }
      },
      {
        "id": "R_roundOf32_3",
        "team1": {
          "name": "Belgium (0.0%)",
          "code": "BEL",
          "score": "L",
          "winner": false
        },
        "team2": {
          "name": "Senegal (100.0%)",
          "code": "SEN",
          "score": "W",
          "winner": true
        }
      },
      {
        "id": "R_roundOf32_4",
        "team1": {
          "name": "Algeria (39.4%)",
          "code": "ALG",
          "score": "L",
          "winner": false
        },
        "team2": {
          "name": "Switzerland (60.6%)",
          "code": "SUI",
          "score": "W",
          "winner": true
        }
      },
      {
        "id": "R_roundOf32_5",
        "team1": {
          "name": "Croatia (43.0%)",
          "code": "CRO",
          "score": "L",
          "winner": false
        },
        "team2": {
          "name": "Portugal (57.0%)",
          "code": "POR",
          "score": "W",
          "winner": true
        }
      },
      {
        "id": "R_roundOf32_6",
        "team1": {
          "name": "Argentina (86.1%)",
          "code": "ARG",
          "score": "W",
          "winner": true
        },
        "team2": {
          "name": "Cape Verde (13.9%)",
          "code": "CPV",
          "score": "L",
          "winner": false
        }
      },
      {
        "id": "R_roundOf32_7",
        "team1": {
          "name": "Australia (54.9%)",
          "code": "AUS",
          "score": "W",
          "winner": true
        },
        "team2": {
          "name": "Egypt (45.1%)",
          "code": "EGY",
          "score": "L",
          "winner": false
        }
      }
    ],
    "roundOf16": [
      {
        "id": "R_roundOf16_0",
        "team1": {
          "name": "Colombia (38.4%)",
          "code": "COL",
          "score": "L",
          "winner": false
        },
        "team2": {
          "name": "Spain (61.6%)",
          "code": "ESP",
          "score": "W",
          "winner": true
        }
      },
      {
        "id": "R_roundOf16_1",
        "team1": {
          "name": "United States (53.5%)",
          "code": "USA",
          "score": "W",
          "winner": true
        },
        "team2": {
          "name": "Senegal (46.5%)",
          "code": "SEN",
          "score": "L",
          "winner": false
        }
      },
      {
        "id": "R_roundOf16_2",
        "team1": {
          "name": "Switzerland (43.7%)",
          "code": "SUI",
          "score": "L",
          "winner": false
        },
        "team2": {
          "name": "Portugal (56.3%)",
          "code": "POR",
          "score": "W",
          "winner": true
        }
      },
      {
        "id": "R_roundOf16_3",
        "team1": {
          "name": "Argentina (76.7%)",
          "code": "ARG",
          "score": "W",
          "winner": true
        },
        "team2": {
          "name": "Australia (23.3%)",
          "code": "AUS",
          "score": "L",
          "winner": false
        }
      }
    ],
    "quarterFinals": [
      {
        "id": "R_quarterFinals_0",
        "team1": {
          "name": "Spain (71.0%)",
          "code": "ESP",
          "score": "W",
          "winner": true
        },
        "team2": {
          "name": "United States (29.0%)",
          "code": "USA",
          "score": "L",
          "winner": false
        }
      },
      {
        "id": "R_quarterFinals_1",
        "team1": {
          "name": "Portugal (37.1%)",
          "code": "POR",
          "score": "L",
          "winner": false
        },
        "team2": {
          "name": "Argentina (62.9%)",
          "code": "ARG",
          "score": "W",
          "winner": true
        }
      }
    ],
    "semiFinals": [
      {
        "id": "R_semiFinals_0",
        "team1": {
          "name": "Spain (49.3%)",
          "code": "ESP",
          "score": "L",
          "winner": false
        },
        "team2": {
          "name": "Argentina (50.7%)",
          "code": "ARG",
          "score": "W",
          "winner": true
        }
      }
    ]
  },
  "final": {
    "id": "F_1",
    "team1": {
      "name": "France (49.2%)",
      "code": "FRA",
      "score": "L",
      "winner": false
    },
    "team2": {
      "name": "Argentina (50.8%)",
      "code": "ARG",
      "score": "W",
      "winner": true
    }
  }
}